dpytools/__init__.py
dpytools/checks.py
dpytools/commands.py
dpytools/embeds.py
dpytools/emojis.py
dpytools/errors.py
dpytools/menus.py
dpytools/parsers.py
dpytools/waiters.py
dpytools-0.18.0b0.dist-info/WHEEL
dpytools-0.18.0b0.dist-info/METADATA
dpytools-0.18.0b0.dist-info/RECORD
