Metadata-Version: 2.1
Name: dpytools
Version: 0.18.0b0
Summary: Easy to use, beginner friendly but powerful tools to speed up discord bots development (discord.py)
Home-page: https://github.com/chrisdewa/dpytools
License: MIT
Keywords: discord,discord.py,discord bot
Author: chrisdewa
Author-email: alexdewa@gmail.com
Requires-Python: >=3.8,<4.0
Classifier: Development Status :: 4 - Beta
Classifier: Intended Audience :: Developers
Classifier: License :: OSI Approved :: MIT License
Classifier: Programming Language :: Python :: 3
Classifier: Programming Language :: Python :: 3.8
Classifier: Programming Language :: Python :: 3.9
Provides-Extra: docs
Requires-Dist: discord.py
Requires-Dist: sphinx (==4.0.2); extra == "docs"
Requires-Dist: sphinx-rtd-theme (==0.5.2); extra == "docs"
Requires-Dist: sphinxcontrib-trio (==1.1.2); extra == "docs"
Project-URL: Documentation, https://dpytools.readthedocs.io/en/master/
Project-URL: Repository, https://github.com/chrisdewa/dpytools
